Workbook

Sheet Resumo
A1: KORP Filial (145) - Fechamento da folha - Contas patrimoniais
A2: Valor pela folha = movimento do mês (crédito - débito). Cada mês tem sua aba com a conferência Folha × TXT.
A4: Conta | B4: Descrição | C4: 05-2026 | D4: 06-2026 | E4: 07-2026 | F4: 08-2026 | G4: 09-2026 | H4: 10-2026 | I4: 11-2026 | J4: 12-2026
A5: 2521 | B5: Salários a Pagar | C5: ='05-2026'!C5 | D5: ='06-2026'!C5
A6: 2523 | B6: Indenizações Trabalhistas (rescisões) | C6: ='05-2026'!C6 | D6: ='06-2026'!C6
A7: 2524 | B7: Férias a Pagar | C7: ='05-2026'!C7 | D7: ='06-2026'!C7
A8: 2526 | B8: Estágios a pagar | C8: ='05-2026'!C8 | D8: ='06-2026'!C8
A9: 2530 | B9: FGTS a Recolher | C9: ='05-2026'!C9 | D9: ='06-2026'!C9
A10: 2531 | B10: INSS a Recolher | C10: ='05-2026'!C10 | D10: ='06-2026'!C10
A11: 2533 | B11: IRRF a Recolher s/ Folha | C11: ='05-2026'!C11 | D11: ='06-2026'!C11
A12: 3137 | B12: Empréstimo a Funcionário (consignado) | C12: ='05-2026'!C12 | D12: ='06-2026'!C12
A13: 2463 | B13: Adiantamento de Férias (ativo) | C13: ='05-2026'!C13 | D13: ='06-2026'!C13
B14: Confere (TXT após ajustes = folha)? | C14: =IF(COUNTIF('05-2026'!H5:H13,"Não")=0,"Sim","Não") | D14: =IF(COUNTIF('06-2026'!H5:H13,"Não")=0,"Sim","Não")

Sheet 05-2026
A1: KORP Filial (145) - Fechamento da folha - Contas patrimoniais - 05/2026
A2: Liquido do extrato 05/2026: 83.431,14 (sem rescisões). Situação: TXT corrigido gerado e importado na Korp.
A4: Conta | B4: Descrição | C4: Valor pela folha (extrato) | D4: Valor no TXT | E4: Diferença | F4: Ajustes identificados | G4: TXT após ajustes | H4: Confere? | I4: Composição dos ajustes
A5: 2521 | B5: Salários a Pagar | C5: 78487.18 | D5: 78065.32 | E5: =C5-D5 | F5: 421.86 | G5: =D5+F5 | H5: =IF(ABS(C5-G5)<1,"Sim","Não") | I5: +3.180,00 salário do Bruno (8781, CC 5) com D/C na mesma conta; -2.961,30 bolsas DES (CC 7 e 13) que vão para 2526; +203,16 afastamento do Michael (CC 8) lançado invertido
A6: 2523 | B6: Indenizações Trabalhistas (rescisões) | C6: 0 | D6: 0 | E6: =C6-D6 | F6: 0 | G6: =D6+F6 | H6: =IF(ABS(C6-G6)<1,"Sim","Não") | I6: Sem rescisões em 05/2026
A7: 2524 | B7: Férias a Pagar | C7: -188.76 | D7: 4146.44 | E7: =C7-D7 | F7: -4335.2 | G7: =D7+F7 | H7: =IF(ABS(C7-G7)<1,"Sim","Não") | I7: +651,08 férias da Atalia não exportadas; -60,24 INSS férias Atalia; -4.926,04 adiantamento de férias (Ana Paula, Atalia, Fernanda) não exportado. Saldo devedor: o adiantamento foi pago antes da folha
A8: 2526 | B8: Estágios a pagar | C8: 5132.72 | D8: 2171.42 | E8: =C8-D8 | F8: 2961.3 | G8: =D8+F8 | H8: =IF(ABS(C8-G8)<1,"Sim","Não") | I8: +2.961,30 bolsas DES (CC 7 e 13) creditadas em 2521
A9: 2530 | B9: FGTS a Recolher | C9: 7558.72 | D9: 7558.72 | E9: =C9-D9 | F9: 0 | G9: =D9+F9 | H9: =IF(ABS(C9-G9)<1,"Sim","Não")
A10: 2531 | B10: INSS a Recolher | C10: 34220.62 | D10: 33988.79 | E10: =C10-D10 | F10: 231.5 | G10: =D10+F10 | H10: =IF(ABS(C10-G10)<1,"Sim","Não") | I10: +171,26 INSS férias Fernanda lançado em 3017; +60,24 INSS férias Atalia não exportado; 0,33 restante = arredondamento
A11: 2533 | B11: IRRF a Recolher s/ Folha | C11: 1039.26 | D11: 1039.26 | E11: =C11-D11 | F11: 0 | G11: =D11+F11 | H11: =IF(ABS(C11-G11)<1,"Sim","Não")
A12: 3137 | B12: Empréstimo a Funcionário (consignado) | C12: 1990.95 | D12: 1990.95 | E12: =C12-D12 | F12: 0 | G12: =D12+F12 | H12: =IF(ABS(C12-G12)<1,"Sim","Não")
A13: 2463 | B13: Adiantamento de Férias (ativo) | C13: 4926.04 | D13: 0 | E13: =C13-D13 | F13: 4926.04 | G13: =D13+F13 | H13: =IF(ABS(C13-G13)<1,"Sim","Não") | I13: Baixa do adiantamento de férias (Ana Paula 2.333,33; Atalia 590,84; Fernanda 2.001,87) não exportada
A15: Salários + Indenizações + Férias + Estágios a pagar
B16: Total | C16: =C5+C6+C7+C8 | D16: =D5+D6+D7+D8 | G16: =G5+G6+G7+G8

Sheet 06-2026
A1: KORP Filial (145) - Fechamento da folha - Contas patrimoniais - 06/2026
A2: Líquido do extrato 06/2026: 87.618,90 + rescisões 7.698,37. Horas extras 100% do Bruno (fora do extrato) mantidas por decisão e somadas ao valor pela folha.
A4: Conta | B4: Descrição | C4: Valor pela folha (extrato) | D4: Valor no TXT | E4: Diferença | F4: Ajustes identificados | G4: TXT após ajustes | H4: Confere? | I4: Composição dos ajustes
A5: 2521 | B5: Salários a Pagar | C5: 78617.06 | D5: 82721.06 | E5: =C5-D5 | F5: -4104 | G5: =D5+F5 | H5: =IF(ABS(C5-G5)<1,"Sim","Não") | I5: Folha = extrato 78.436,90 + 180,16 horas extras do Bruno mantidas. Ajustes: -6.790,00 bolsas (CC 7, 13 e 16) para 2526; +2.756,00 salário do Bruno (8781, CC 5) com D/C na mesma conta; -70,00 contribuição do CC 14 invertida
A6: 2523 | B6: Indenizações Trabalhistas (rescisões) | C6: 7698.37 | D6: 1982.4 | E6: =C6-D6 | F6: 5715.97 | G6: =D6+F6 | H6: =IF(ABS(C6-G6)<1,"Sim","Não") | I6: +5.583,50 rescisão do Antônio Henrique (CC 7) não exportada; +132,47 lançados nas contas 252/253 (rescisões Edgard e Marina)
A7: 2524 | B7: Férias a Pagar | C7: 0 | D7: 0 | E7: =C7-D7 | F7: 0 | G7: =D7+F7 | H7: =IF(ABS(C7-G7)<1,"Sim","Não") | I7: Sem férias na folha de 06/2026
A8: 2526 | B8: Estágios a pagar | C8: 9182 | D8: 2392 | E8: =C8-D8 | F8: 6790 | G8: =D8+F8 | H8: =IF(ABS(C8-G8)<1,"Sim","Não") | I8: +6.790,00 bolsas creditadas em 2521 (CC 7: 2.890,00; CC 13: 2.600,00; CC 16: 1.300,00)
A9: 2530 | B9: FGTS a Recolher | C9: 8003.69 | D9: 7466.04 | E9: =C9-D9 | F9: 537.65 | G9: =D9+F9 | H9: =IF(ABS(C9-G9)<1,"Sim","Não") | I9: Folha = Valor do FGTS 7.449,67 + FGTS rescisório do Antônio Henrique 537,65 + 16,37 horas extras do Bruno mantidas. Ajuste: +537,65 FGTS da rescisão do Antônio não exportado
A10: 2531 | B10: INSS a Recolher | C10: 34963.59 | D10: 34648.06 | E10: =C10-D10 | F10: 315.15 | G10: =D10+F10 | H10: =IF(ABS(C10-G10)<1,"Sim","Não") | I10: Folha = Total INSS 34.884,20 + 79,39 horas extras do Bruno mantidas. Ajuste: +315,15 INSS da rescisão do Antônio Henrique; 0,38 restante = arredondamento
A11: 2533 | B11: IRRF a Recolher s/ Folha | C11: 833.86 | D11: 833.86 | E11: =C11-D11 | F11: 0 | G11: =D11+F11 | H11: =IF(ABS(C11-G11)<1,"Sim","Não")
A12: 3137 | B12: Empréstimo a Funcionário (consignado) | C12: 2248.56 | D12: 2248.56 | E12: =C12-D12 | F12: 0 | G12: =D12+F12 | H12: =IF(ABS(C12-G12)<1,"Sim","Não")
A13: 2463 | B13: Adiantamento de Férias (ativo) | C13: 0 | D13: 0 | E13: =C13-D13 | F13: 0 | G13: =D13+F13 | H13: =IF(ABS(C13-G13)<1,"Sim","Não") | I13: Sem adiantamento de férias descontado em 06/2026
A15: Salários + Indenizações + Férias + Estágios a pagar
B16: Total | C16: =C5+C6+C7+C8 | D16: =D5+D6+D7+D8 | G16: =G5+G6+G7+G8
