Workbook

Sheet RESUMO
A1: Como usar
A2: TXT único jan-ago/2026 pronto para importar. A coluna G (CONTA FINAL) da aba LANCAMENTOS é o que está no TXT - não precisa preencher nada.
A3: Cores: vermelho = corrigido pelo Cosmos; salmão = ajustado por decisão (regras na aba DECISOES); verde = jul/ago; amarelo = mantida a conta atual; sem cor = OK.
A4: No Domínio: excluir TODOS os lançamentos do Itaú (conta 8) de 01/01 a 30/06/2026 e importar o TXT único (jan a ago).
A5: Aplicação automática Itaú não segregada: conta 8 = saldo total (C/C + aplicação); aplicações/resgates fora; rendimentos na 432.
A6: Saldo calculado = extrato Itaú em todos os meses (aba CONCILIACAO).
A8: Status | B8: Qtde | C8: Valor absoluto
A9: AJUSTADO | B9: 205 | C9: 1015303.3
A10: SEM COSMOS | B10: 735 | C10: 2359210.6
A11: OK | B11: 647 | C11: 1533653
A12: CORRIGIR | B12: 55 | C12: 90586.82
A13: MANTIDO | B13: 129 | C13: 348582.63
A14: CORRIGIDO | B14: 18 | C14: 51798.35

Sheet DECISOES
A1: Assunto | B1: Regra aplicada | C1: Base
A2: Empresas do grupo | B2: Uma conta-corrente de mútuo por empresa, entradas e saídas na mesma conta: COSMETICON 663, F.V.S 662, CABELO MEU 670, GULA/FIQUE BEM 366 | C2: Cosmos lança como OUTRAS ENTRADAS/SAÍDAS (não é venda/compra com nota). Protection faz a contabilidade de Cosmetici, Cosmeticon, FVS e Gula = grupo. Fique Bem tem o mesmo CNPJ da Gula (30.415.972/0001-08).
A3: Pagamentos à GULA/FIQUE BEM | B3: Saem de Fornecedores (506) e vão para 366 | C3: Não há compra com nota; explica parte do saldo devedor de 180 mil da 506.
A4: Amortização de empréstimos (Selito Kosdra, MRBS) | B4: 672 EMPRESTIMO DE TERCEIRO (antes despesa 362/364/493) | C4: Cosmos: parcelas de empréstimos de 116.000 / 300.000 / 60.000. Juros desses empréstimos ficam em 375.
A5: Claudia A. Rubin - devolução de 53.200,00 (estande Beauty Fair) | B5: 688 FEIRAS E EVENTOS (antes 362) | C5: Cosmos: devolução referente a 30% do estande da Beauty Fair comprado pelos chineses = custo da feira.
A6: Beauty Fair - acordo | B6: 688 FEIRAS E EVENTOS (antes 506) | C6: Contrato de feira/estande.
A7: Comissões sobre vendas (Cosmos cat. 53) | B7: 308 COMISSÕES | C7: Conta existente no plano (balancete 2025).
A8: RNX FIDC - troca de boletos/antecipação | B8: 504 CLIENTES DIVERSOS | C8: Recompra de títulos antecipados.
A9: LINK BANK 3 x 2.142,00 (jan/fev) | B9: 506 (antes 432 rendimentos) | C9: Parcelas AMONEX (matéria-prima) - Cosmos 18/02.
A10: Pessoas físicas pagas como serviço/comissão | B10: 362 (antes 506/25/187/493) | C10: Sem nota no fiscal; empresa sem folha desde 03/26.
A11: Sistemas (CRMTECH, Tecnoponto, VR ponto, desenvolvedores) | B11: 640 | C11: Cosmos cat. 47.
A12: Protection | B12: 361 | C12: Honorários contábeis.
... A16: Aplicação automática Itaú | B16: Não segregada | C16: Orientação do escritório: conta 8 = saldo total.

Sheet LANCAMENTOS jan-ago
A1: Nº | B1: Data | C1: Histórico extrato/razão (original) | D1: Valor (+ entrada / - saída) | E1: Conta atual no Domínio | F1: Descrição conta atual | G1: CONTA FINAL (vai no TXT) | H1: Descrição conta final | I1: Sugestão | J1: Status | K1: Motivo | L1: Relatório Cosmos (fornecedor | OP/PF | descrição) | M1: Histórico que vai no TXT
A2: 1 | B2: 02/01/2026 | C2: REF. A SISPAG COSMETICON COMER | D2: 12000 | E2: 663 | F2: EMPRESTIMO COSMETICON COMERCIO (31.494.732/0001-09) | G2: 663 | H2: =IFERROR(VLOOKUP(G2&"",PLANO!A:B,2,FALSE),"CONTA NAO EXISTE NO PLANO") | I2: 663 | J2: AJUSTADO | K2: COSMETICON - conta-corrente unica de mutuo (663) | L2: OUTRAS ENTRADAS | 122/71 | | M2: SISPAG COSMETICON COMER
A3: 2 | B3: 02/01/2026 | C3: PIX ENVIADO MARIANE POSS | D3: -683.1 | E3: 187 | F3: SALÁRIOS E ORDENADOS A PAGAR | G3: 187 | H3: =IFERROR(VLOOKUP(G3&"",PLANO!A:B,2,FALSE),"CONTA NAO EXISTE NO PLANO") | I3: 187 | J3: SEM COSMOS | M3: PIX ENVIADO MARIANE POSS
A4: 3 | B4: 02/01/2026 | C4: REF. A PIX ENVIADO ROSANE DA SI | D4: -683.1 | E4: 187 | F4: SALÁRIOS E ORDENADOS A PAGAR | G4: 187 | H4: =IFERROR(VLOOKUP(G4&"",PLANO!A:B,2,FALSE),"CONTA NAO EXISTE NO PLANO") | I4: 187 | J4: SEM COSMOS | M4: PIX ENVIADO ROSANE DA SI
A5: 4 | B5: 02/01/2026 | C5: REF. A PIX ENVIADO ADRIA FAGUND | D5: -143.71 | E5: 187 | F5: SALÁRIOS E ORDENADOS A PAGAR | G5: 187 | H5: =IFERROR(VLOOKUP(G5&"",PLANO!A:B,2,FALSE),"CONTA NAO EXISTE NO PLANO") | I5: 187 | J5: SEM COSMOS | M5: PIX ENVIADO ADRIA FAGUND
A6: 5 | B6: 02/01/2026 | C6: REF. A PIX ENVIADO GRACIELE APA | D6: -574.86 | E6: 187 | F6: SALÁRIOS E ORDENADOS A PAGAR | G6: 187 | H6: =IFERROR(VLOOKUP(G6&"",PLANO!A:B,2,FALSE),"CONTA NAO EXISTE NO PLANO") | I6: 187 | J6: SEM COSMOS | M6: PIX ENVIADO GRACIELE APA
A7: 6 | B7: 02/01/2026 | C7: SKIN LAB INDUSTRIA E COMERCIO DE COSMETICOS LTDA PAGAMENTO REFERENTE A COMPRA DE RESORCINOL 25KG.MAP 5KG, VASELINA 198KG E ERITORBATO 25KG | D7: -2745 | E7: 506 | F7: FORNECEDORES DIVERSOS | G7: 506 | H7: =IFERROR(VLOOKUP(G7&"",PLANO!A:B,2,FALSE),"CONTA NAO EXISTE NO PLANO") | I7: 506 | J7: OK | K7: fornecedor com NF | L7: SKIN LAB INDUSTRIA E COMERCIO DE COSMETICOS LTDA | 115/6 | PAGAMENTO REFERENTE A COMPRA DE RESORCINOL 25KG. MAP 5KG, VASELINA 198KG E ERITORBATO 25KG | M7: SKIN LAB INDUSTRIA E COMERCIO DE COSMETICOS LTDA - PAGAMENTO REFERENTE A COMPRA DE RESORCINOL 25KG. MAP 5KG, VASELINA 198KG E ERITO
A8: 7 | B8: 02/01/2026 | C8: REF. A PIX ENVIADO BRUNA CARLA | D8: -574.86 | E8: 187 | F8: SALÁRIOS E ORDENADOS A PAGAR | G8: 187 | H8: =IFERROR(VLOOKUP(G8&"",PLANO!A:B,2,FALSE),"CONTA NAO EXISTE NO PLANO") | I8: 187 | J8: SEM COSMOS | M8: PIX ENVIADO BRUNA CARLA
A9: 8 | B9: 02/01/2026 | C9: REF. A PIX ENVIADO THIAGO HENRI | D9: -900 | E9: 362 | F9: SERVIÇOS PRESTADOS POR TERCEIROS | G9: 362 | H9: =IFERROR(VLOOKUP(G9&"",PLANO!A:B,2,FALSE),"CONTA NAO EXISTE NO PLANO") | I9: 362 | J9: SEM COSMOS | M9: PIX ENVIADO THIAGO HENRI
A10: 9 | B10: 02/01/2026 | C10: REF. A PIX ENVIADO LUZIA ALVES | D10: -574.86 | E10: 187 | F10: SALÁRIOS E ORDENADOS A PAGAR | G10: 187 | H10: =IFERROR(VLOOKUP(G10&"",PLANO!A:B,2,FALSE),"CONTA NAO EXISTE NO PLANO") | I10: 187 | J10: SEM COSMOS | M10: PIX ENVIADO LUZIA ALVES
A11: 10 | B11: 02/01/2026 | C11: REF. A PIX ENVIADO BRUNA SOARES | D11: -526.95 | E11: 187 | F11: SALÁRIOS E ORDENADOS A PAGAR | G11: 187 | H11: =IFERROR(VLOOKUP(G11&"",PLANO!A:B,2,FALSE),"CONTA NAO EXISTE NO PLANO") | I11: 187 | J11: SEM COSMOS | M11: PIX ENVIADO BRUNA SOARES
A12: 11 | B12: 02/01/2026 | C12: PIX ENVIADO CARLOS ALBER | D12: -970.5 | E12: 187 | F12: SALÁRIOS E ORDENADOS A PAGAR | G12: 187 | H12: =IFERROR(VLOOKUP(G12&"",PLANO!A:B,2,FALSE),"CONTA NAO EXISTE NO PLANO") | I12: 187 | J12: SEM COSMOS | M12: PIX ENVIADO CARLOS ALBER
A13: 12 | B13: 02/01/2026 | C13: REF. A PIX ENVIADO ELIANE VAZ P | D13: -683.1 | E13: 187 | F13: SALÁRIOS E ORDENADOS A PAGAR | G13: 187 | H13: =IFERROR(VLOOKUP(G13&"",PLANO!A:B,2,FALSE),"CONTA NAO EXISTE NO PLANO") | I13: 187 | J13: SEM COSMOS | M13: PIX ENVIADO ELIANE VAZ P
A14: 13 | B14: 02/01/2026 | C14: REF. A PIX ENVIADO EVA APARECID | D14: -816.6 | E14: 187 | F14: SALÁRIOS E ORDENADOS A PAGAR | G14: 187 | H14: =IFERROR(VLOOKUP(G14&"",PLANO!A:B,2,FALSE),"CONTA NAO EXISTE NO PLANO") | I14: 187 | J14: SEM COSMOS | M14: PIX ENVIADO EVA APARECID
A15: 14 | B15: 02/01/2026 | C15: REF. A PIX ENVIADO LUIZ FELIPE | D15: -683.1 | E15: 187 | F15: SALÁRIOS E ORDENADOS A PAGAR | G15: 187 | H15: =IFERROR(VLOOKUP(G15&"",PLANO!A:B,2,FALSE),"CONTA NAO EXISTE NO PLANO") | I15: 187 | J15: SEM COSMOS | M15: PIX ENVIADO LUIZ FELIPE
A16: 15 | B16: 02/01/2026 | C16: PIX ENVIADO LUCIANO PERE | D16: -970.5 | E16: 187 | F16: SALÁRIOS E ORDENADOS A PAGAR | G16: 187 | H16: =IFERROR(VLOOKUP(G16&"",PLANO!A:B,2,FALSE),"CONTA NAO EXISTE NO PLANO") | I16: 187 | J16: SEM COSMOS | M16: PIX ENVIADO LUCIANO PERE
A17: 16 | B17: 02/01/2026 | C17: REF. A PIX ENVIADO MARCOS PAULO | D17: -683.1 | E17: 187 | F17: SALÁRIOS E ORDENADOS A PAGAR | G17: 187 | H17: =IFERROR(VLOOKUP(G17&"",PLANO!A:B,2,FALSE),"CONTA NAO EXISTE NO PLANO") | I17: 187 | J17: SEM COSMOS | M17: PIX ENVIADO MARCOS PAULO
A18: 17 | B18: 02/01/2026 | C18: AQIA QUIMICA INOVATIVA LTDAPGTO REF. A COMPRA DE MATERIA PRIMA | D18: -1943.47 | E18: 506 | F18: FORNECEDORES DIVERSOS | G18: 506 | H18: =IFERROR(VLOOKUP(G18&"",PLANO!A:B,2,FALSE),"CONTA NAO EXISTE NO PLANO") | I18: 506 | J18: OK | K18: fornecedor com NF | L18: AQIA QUIMICA INOVATIVA LTDA | 115/6 | PGTO REF. A COMPRA DE MATERIA PRIMA | M18: AQIA QUIMICA INOVATIVA LTDA - PGTO REF. A COMPRA DE MATERIA PRIMA
A19: 18 | B19: 02/01/2026 | C19: BARENTZ BRASIL DISTRIBUIDORA LTDAPGTO REF. A COMPRA DE MATERIA PRIMA | D19: -1511.29 | E19: 506 | F19: FORNECEDORES DIVERSOS | G19: 506 | H19: =IFERROR(VLOOKUP(G19&"",PLANO!A:B,2,FALSE),"CONTA NAO EXISTE NO PLANO") | I19: 506 | J19: OK | K19: fornecedor com NF | L19: BARENTZ BRASIL DISTRIBUIDORA LTDA | 115/6 | PGTO REF. A COMPRA DE MATERIA PRIMA | M19: BARENTZ BRASIL DISTRIBUIDORA LTDA - PGTO REF. A COMPRA DE MATERIA PRIMA
A20: 19 | B20: 02/01/2026 | C20: MASTER PUMPS EMBALAGENS COMERCIO IMPORTACAO E EXPORTACAO LTDA | D20: -714.84 | E20: 506 | F20: FORNECEDORES DIVERSOS | G20: 506 | H20: =IFERROR(VLOOKUP(G20&"",PLANO!A:B,2,FALSE),"CONTA NAO EXISTE NO PLANO") | I20: 506 | J20: OK | K20: fornecedor com NF | L20: MASTER PUMPS EMBALAGENS COMERCIO IMPORTACAO E EXPORTACAO LTDA | 115/9 | PGTO REF. A COMPRA DE EMBALAGEM | M20: MASTER PUMPS EMBALAGENS COMERCIO IMPORTACAO E EXPORTACAO LTDA - PGTO REF. A COMPRA DE EMBALAGEM
A21: 20 | B21: 02/01/2026 | C21: MASTER PUMPS EMBALAGENS COMERCIO IMPORTACAO E EXPORTACAO LTDA PGTO REF. A COMPRA DE FRASCO | D21: -1068.36 | E21: 506 | F21: FORNECEDORES DIVERSOS | G21: 506 | H21: =IFERROR(VLOOKUP(G21&"",PLANO!A:B,2,FALSE),"CONTA NAO EXISTE NO PLANO") | I21: 506 | J21: OK | K21: fornecedor com NF | L21: MASTER PUMPS EMBALAGENS COMERCIO IMPORTACAO E EXPORTACAO LTDA | 115/9 | PGTO REF. A COMPRA DE FRASCO | M21: MASTER PUMPS EMBALAGENS COMERCIO IMPORTACAO E EXPORTACAO LTDA - PGTO REF. A COMPRA DE FRASCO
A22: 21 | B22: 02/01/2026 | C22: MULTIQUIM INDUSTRIA COMERCIO IMPORTACAO E EXP LTDA PGTO REF. A COMPRA DE ACIDO TIOGLICOLICO 160 KG | D22: -5063.97 | E22: 506 | F22: FORNECEDORES DIVERSOS | G22: 506 | H22: =IFERROR(VLOOKUP(G22&"",PLANO!A:B,2,FALSE),"CONTA NAO EXISTE NO PLANO") | I22: 506 | J22: OK | K22: fornecedor com NF | L22: MULTIQUIM INDUSTRIA COMERCIO IMPORTACAO E EXP LTDA | 115/97 | PGTO REF. A COMPRA DE ACIDO TIOGLICOLICO 160 KG | M22: MULTIQUIM INDUSTRIA COMERCIO IMPORTACAO E EXP LTDA - PGTO REF. A COMPRA DE ACIDO TIOGLICOLICO 160 KG
A23: 22 | B23: 02/01/2026 | C23: QUIMIFORMULA COMERCIO DE PRODUTOS QUIMICOS LTDAPGTO REF. A COMPRA DE MATERIA PRIMA, GENAMIN KDMP20 KG | D23: -1211.83 | E23: 506 | F23: FORNECEDORES DIVERSOS | G23: 506 | H23: =IFERROR(VLOOKUP(G23&"",PLANO!A:B,2,FALSE),"CONTA NAO EXISTE NO PLANO") | I23: 506 | J23: OK | K23: fornecedor com NF | L23: QUIMIFORMULA COMERCIO DE PRODUTOS QUIMICOS LTDA | 115/6 | PGTO REF. A COMPRA DE MATERIA PRIMA, GENAMIN KDMP 20 KG | M23: QUIMIFORMULA COMERCIO DE PRODUTOS QUIMICOS LTDA - PGTO REF. A COMPRA DE MATERIA PRIMA, GENAMIN KDMP 20 KG
A24: 23 | B24: 02/01/2026 | C24: COSMOTEC INTERNATIONAL ESPECIALIDADES COSMETICAS LTDA.PAGAMENTO REFERENTE A COMPRA DE MATERIA PRIMA,SF1550 - 5KG, SF1214 - 190KG, SF 876 - 5KG | D24: -2080.75 | E24: 506 | F24: FORNECEDORES DIVERSOS | G24: 506 | H24: =IFERROR(VLOOKUP(G24&"",PLANO!A:B,2,FALSE),"CONTA NAO EXISTE NO PLANO") | I24: 506 | J24: OK | K24: fornecedor com NF | L24: COSMOTEC INTERNATIONAL ESPECIALIDADES COSMETICAS LTDA. | 115/6 | PAGAMENTO REFERENTE A COMPRA DE MATERIA PRIMA, SF1550 - 5KG, SF1214 - 190KG, SF 876 - 5KG | M24: COSMOTEC INTERNATIONAL ESPECIALIDADES COSMETICAS LTDA. - PAGAMENTO REFERENTE A COMPRA DE MATERIA PRIMA, SF1550 - 5KG, SF1214 - 190KG, SF
A25: 24 | B25: 02/01/2026 | C25: YAHWEH PRINT BRASIL LTDAPGTO REF. A COMPRA DE ROTULO CELULA TRONCO | D25: -2968.15 | E25: 506 | F25: FORNECEDORES DIVERSOS | G25: 506 | H25: =IFERROR(VLOOKUP(G25&"",PLANO!A:B,2,FALSE),"CONTA NAO EXISTE NO PLANO") | I25: 506 | J25: OK | K25: fornecedor com NF | L25: YAHWEH PRINT BRASIL LTDA | 115/9 | PGTO REF. A COMPRA DE ROTULO CELULA TRONCO | M25: YAHWEH PRINT BRASIL LTDA - PGTO REF. A COMPRA DE ROTULO CELULA TRONCO
A26: 25 | B26: 02/01/2026 | C26: BANCO ITAU UNIBANCO PAGTO REF. JUROS EXCESSO LIMITE CONTA | D26: -51.73 | E26: 372 | F26: JUROS DE MORA | G26: 372 | H26: =IFERROR(VLOOKUP(G26&"",PLANO!A:B,2,FALSE),"CONTA NAO EXISTE NO PLANO") | I26: 372 | J26: OK | K26: juros limite (375/625) | L26: BANCO ITAU UNIBANCO | 115/122 | PAGTO REF. JUROS EXCESSO LIMITE CONTA | M26: BANCO ITAU UNIBANCO - PAGTO REF. JUROS EXCESSO LIMITE CONTA
A27: 26 | B27: 05/01/2026 | C27: REF. A MOV TIT COB DISP 05/01S | D27: 7514.46 | E27: 504 | F27: CLIENTES DIVERSOS | G27: 504 | H27: =IFERROR(VLOOKUP(G27&"",PLANO!A:B,2,FALSE),"CONTA NAO EXISTE NO PLANO") | I27: 504 | J27: SEM COSMOS | M27: MOV TIT COB DISP 05/01S
A28: 27 | B28: 05/01/2026 | C28: REF. A REDE MAST AT0081996543 | D28: 8888.62 | E28: 504 | F28: CLIENTES DIVERSOS | G28: 504 | H28: =IFERROR(VLOOKUP(G28&"",PLANO!A:B,2,FALSE),"CONTA NAO EXISTE NO PLANO") | I28: 504 | J28: SEM COSMOS | M28: REDE MAST AT0081996543
A29: 28 | B29: 05/01/2026 | C29: REF. A REDE VISA AT0081996543 | D29: 2400.47 | E29: 504 | F29: CLIENTES DIVERSOS | G29: 504 | H29: =IFERROR(VLOOKUP(G29&"",PLANO!A:B,2,FALSE),"CONTA NAO EXISTE NO PLANO") | I29: 504 | J29: SEM COSMOS | M29: REDE VISA AT0081996543
A30: 29 | B30: 05/01/2026 | C30: PGTO REF. JUROS LIMITE CONTA + IOF | D30: -139.81 | E30: 625 | F30: IOF | G30: 625 | H30: =IFERROR(VLOOKUP(G30&"",PLANO!A:B,2,FALSE),"CONTA NAO EXISTE NO PLANO") | I30: 625 | J30: OK | K30: juros limite (375/625) | L30: BANCO ITAU UNIBANCO | 115/122 | PGTO REF. JUROS LIMITE CONTA + IOF | M30: BANCO ITAU UNIBANCO - PGTO REF. JUROS LIMITE CONTA + IOF
A31: 30 | B31: 05/01/2026 | C31: FLASH TECNOLOGIA E INSTITUICAO DE PAGAMENTO LTDA PGTO REF.VALE ALIMENTAÇÃO | D31: -10305 | E31: 659 | F31: VA / VR | G31: 659 | H31: =IFERROR(VLOOKUP(G31&"",PLANO!A:B,2,FALSE),"CONTA NAO EXISTE NO PLANO") | I31: 659 | J31: OK | K31: categoria Cosmos 34 | L31: FLASH TECNOLOGIA E INSTITUICAO DE PAGAMENTO LTDA | 115/34 | PGTO REF.VALE ALIMENTAÇÃO | M31: FLASH TECNOLOGIA E INSTITUICAO DE PAGAMENTO LTDA - PGTO REF.VALE ALIMENTAÇÃO
A32: 31 | B32: 05/01/2026 | C32: BANCO ITAU UNIBANCOPGTO REF. JUROS LIMITE CONTA + IOF | D32: -392.12 | E32: 625 | F32: IOF | G32: 625 | H32: =IFERROR(VLOOKUP(G32&"",PLANO!A:B,2,FALSE),"CONTA NAO EXISTE NO PLANO") | I32: 625 | J32: OK | K32: juros limite (375/625) | L32: BANCO ITAU UNIBANCO | 115/122 | PGTO REF. JUROS LIMITE CONTA + IOF | M32: BANCO ITAU UNIBANCO - PGTO REF. JUROS LIMITE CONTA + IOF
A33: 32 | B33: 05/01/2026 | C33: BEATRIZ CAMILA MARCELINO DOS SANTOSPGTO REF. A VALE TRANSPORTE+VALE REFEIÇÃO | D33: -456 | E33: 187 | F33: SALÁRIOS E ORDENADOS A PAGAR | G33: 659 | H33: =IFERROR(VLOOKUP(G33&"",PLANO!A:B,2,FALSE),"CONTA NAO EXISTE NO PLANO") | I33: 659 | J33: CORRIGIR | K33: categoria Cosmos 34 | L33: BEATRIZ CAMILA MARCELINO DOS SANTOS | 115/34 | PGTO REF. A VALE TRANSPORTE+VALE REFEIÇÃO | M33: BEATRIZ CAMILA MARCELINO DOS SANTOS - PGTO REF. A VALE TRANSPORTE+VALE REFEIÇÃO
A34: 33 | B34: 05/01/2026 | C34: TRANS TOMAZ - TRANSPORTES RODOVIARIOS DE CARGAS EIRELIPGTO REF. A FRETE SOBRE COMPRAS | D34: -264.01 | E34: 312 | F34: FRETES E CARRETOS | G34: 312 | H34: =IFERROR(VLOOKUP(G34&"",PLANO!A:B,2,FALSE),"CONTA NAO EXISTE NO PLANO") | I34: 312 | J34: OK | K34: categoria Cosmos 4 | L34: TRANS TOMAZ TRANSPORTES RODOVIARIOS DE CARGAS EIRELI | 115/4 | PGTO REF. A FRETE SOBRE COMPRAS | M34: TRANS TOMAZ TRANSPORTES RODOVIARIOS DE CARGAS EIRELI - PGTO REF. A FRETE SOBRE COMPRAS
A35: 34 | B35: 05/01/2026 | C35: BANCO ITAU UNIBANCOPGTO REF. JUROS LIMITE CONTA + IOF | D35: -7217.03 | E35: 375 | F35: JUROS SOBRE EMPRÉSTIMOS E FINANCIAMENTOS | G35: 375 | H35: =IFERROR(VLOOKUP(G35&"",PLANO!A:B,2,FALSE),"CONTA NAO EXISTE NO PLANO") | I35: 375 | J35: OK | K35: juros limite (375/625) | L35: BANCO ITAU UNIBANCO | 115/122 | PGTO REF. JUROS LIMITE CONTA + IOF | M35: BANCO ITAU UNIBANCO - PGTO REF. JUROS LIMITE CONTA + IOF
A36: 35 | B36: 05/01/2026 | C36: BANCO ITAU UNIBANCOPAGTO REF. TAR COB EXP+PIX TRANSF. | D36: -66.6 | E36: 626 | F36: TARIFAS BANCARIAS | G36: 626 | H36: =IFERROR(VLOOKUP(G36&"",PLANO!A:B,2,FALSE),"CONTA NAO EXISTE NO PLANO") | I36: 626 | J36: OK | K36: tarifa/IOF bancario | L36: BANCO ITAU UNIBANCO | 115/56 | PAGTO REF. TAR COB EXP+PIX TRANSF. | M36: BANCO ITAU UNIBANCO - PAGTO REF. TAR COB EXP+PIX TRANSF.
A37: 36 | B37: 05/01/2026 | C37: BANCO ITAU UNIBANCOPAGTO REF. TAR COB EXP+PIX TRANSF. | D37: -400.88 | E37: 626 | F37: TARIFAS BANCARIAS | G37: 626 | H37: =IFERROR(VLOOKUP(G37&"",PLANO!A:B,2,FALSE),"CONTA NAO EXISTE NO PLANO") | I37: 626 | J37: OK | K37: tarifa/IOF bancario | L37: BANCO ITAU UNIBANCO | 115/56 | PAGTO REF. TAR COB EXP+PIX TRANSF. | M37: BANCO ITAU UNIBANCO - PAGTO REF. TAR COB EXP+PIX TRANSF.
A38: 37 | B38: 06/01/2026 | C38: REF. A SISPAG COSMETICON COMER (OUTRAS ENTRADAS) | D38: 8000 | E38: 663 | F38: EMPRESTIMO COSMETICON COMERCIO (31.494.732/0001-09) | G38: 663 | H38: =IFERROR(VLOOKUP(G38&"",PLANO!A:B,2,FALSE),"CONTA NAO EXISTE NO PLANO") | I38: 663 | J38: AJUSTADO | K38: COSMETICON - conta-corrente unica de mutuo (663) | L38: OUTRAS ENTRADAS | 122/71 | | M38: SISPAG COSMETICON COMER (OUTRAS ENTRADAS)
A39: 38 | B39: 06/01/2026 | C39: REF. A MOV TIT COB DISP 06/01S | D39: 1401.83 | E39: 504 | F39: CLIENTES DIVERSOS | G39: 504 | H39: =IFERROR(VLOOKUP(G39&"",PLANO!A:B,2,FALSE),"CONTA NAO EXISTE NO PLANO") | I39: 504 | J39: SEM COSMOS | M39: MOV TIT COB DISP 06/01S
A40: 39 | B40: 06/01/2026 | C40: REF. A PIX TRANSF SINDICO06/01 | D40: 4611.6 | E40: 504 | F40: CLIENTES DIVERSOS | G40: 504 | H40: =IFERROR(VLOOKUP(G40&"",PLANO!A:B,2,FALSE),"CONTA NAO EXISTE NO PLANO") | I40: 504 | J40: SEM COSMOS | M40: PIX TRANSF SINDICO06/01
A41: 40 | B41: 06/01/2026 | C41: REF. A PIX ENVIADO BRUNA CARLA | D41: -1098 | E41: 187 | F41: SALÁRIOS E ORDENADOS A PAGAR | G41: 187 | H41: =IFERROR(VLOOKUP(G41&"",PLANO!A:B,2,FALSE),"CONTA NAO EXISTE NO PLANO") | I41: 187 | J41: SEM COSMOS | M41: PIX ENVIADO BRUNA CARLA
A42: 41 | B42: 06/01/2026 | C42: REF. A PIX ENVIADO ELIANE VAZ P | D42: -1669 | E42: 187 | F42: SALÁRIOS E ORDENADOS A PAGAR | G42: 187 | H42: =IFERROR(VLOOKUP(G42&"",PLANO!A:B,2,FALSE),"CONTA NAO EXISTE NO PLANO") | I42: 187 | J42: SEM COSMOS | M42: PIX ENVIADO ELIANE VAZ P
A43: 42 | B43: 06/01/2026 | C43: REF. A PIX ENVIADO EVA APARECID | D43: -1983 | E43: 187 | F43: SALÁRIOS E ORDENADOS A PAGAR | G43: 187 | H43: =IFERROR(VLOOKUP(G43&"",PLANO!A:B,2,FALSE),"CONTA NAO EXISTE NO PLANO") | I43: 187 | J43: SEM COSMOS | M43: PIX ENVIADO EVA APARECID
A44: 43 | B44: 06/01/2026 | C44: PIX ENVIADO LUCIANO PERE | D44: -2044 | E44: 187 | F44: SALÁRIOS E ORDENADOS A PAGAR | G44: 187 | H44: =IFERROR(VLOOKUP(G44&"",PLANO!A:B,2,FALSE),"CONTA NAO EXISTE NO PLANO") | I44: 187 | J44: SEM COSMOS | M44: PIX ENVIADO LUCIANO PERE
A45: 44 | B45: 06/01/2026 | C45: REF. A PIX ENVIADO ROSANE DA SI | D45: -1350 | E45: 187 | F45: SALÁRIOS E ORDENADOS A PAGAR | G45: 187 | H45: =IFERROR(VLOOKUP(G45&"",PLANO!A:B,2,FALSE),"CONTA NAO EXISTE NO PLANO") | I45: 187 | J45: SEM COSMOS | M45: PIX ENVIADO ROSANE DA SI
A46: 45 | B46: 06/01/2026 | C46: PIX ENVIADO CARLOS ALBER | D46: -1644 | E46: 187 | F46: SALÁRIOS E ORDENADOS A PAGAR | G46: 187 | H46: =IFERROR(VLOOKUP(G46&"",PLANO!A:B,2,FALSE),"CONTA NAO EXISTE NO PLANO") | I46: 187 | J46: SEM COSMOS | M46: PIX ENVIADO CARLOS ALBER
A47: 46 | B47: 06/01/2026 | C47: REF. A PIX ENVIADO LUZIA ALVES | D47: -1120 | E47: 511 | F47: FÉRIAS A PAGAR | G47: 511 | H47: =IFERROR(VLOOKUP(G47&"",PLANO!A:B,2,FALSE),"CONTA NAO EXISTE NO PLANO") | I47: 511 | J47: SEM COSMOS | M47: PIX ENVIADO LUZIA ALVES
A48: 47 | B48: 06/01/2026 | C48: REF. A PIX ENVIADO BRUNA SOARES | D48: -1123 | E48: 511 | F48: FÉRIAS A PAGAR | G48: 511 | H48: =IFERROR(VLOOKUP(G48&"",PLANO!A:B,2,FALSE),"CONTA NAO EXISTE NO PLANO") | I48: 511 | J48: SEM COSMOS | M48: PIX ENVIADO BRUNA SOARES
A49: 48 | B49: 06/01/2026 | C49: BOLETO PAGO EXPRESSO SAO | D49: -351.64 | E49: 312 | F49: FRETES E CARRETOS | G49: 312 | H49: =IFERROR(VLOOKUP(G49&"",PLANO!A:B,2,FALSE),"CONTA NAO EXISTE NO PLANO") | I49: 312 | J49: SEM COSMOS | M49: BOLETO PAGO EXPRESSO SAO
A50: 49 | B50: 06/01/2026 | C50: TEX COURIER S.APAG REF A FRETE SOBRE VENDAS | D50: -671.68 | E50: 312 | F50: FRETES E CARRETOS | G50: 312 | H50: =IFERROR(VLOOKUP(G50&"",PLANO!A:B,2,FALSE),"CONTA NAO EXISTE NO PLANO") | I50: 312 | J50: OK | K50: categoria Cosmos 97 | L50: TEX COURIER S.A | 115/97 | PAG REF A FRETE SOBRE VENDAS | M50: TEX COURIER S.A - PAG REF A FRETE SOBRE VENDAS
A51: 50 | B51: 07/01/2026 | C51: REF. A SISPAG COSMETICON COMER (OUTRAS ENTRADAS) | D51: 30000 | E51: 663 | F51: EMPRESTIMO COSMETICON COMERCIO (31.494.732/0001-09) | G51: 663 | H51: =IFERROR(VLOOKUP(G51&"",PLANO!A:B,2,FALSE),"CONTA NAO EXISTE NO PLANO") | I51: 663 | J51: AJUSTADO | K51: COSMETICON - conta-corrente unica de mutuo (663) | L51: OUTRAS ENTRADAS | 122/71 | | M51: SISPAG COSMETICON COMER (OUTRAS ENTRADAS)
A52: 51 | B52: 07/01/2026 | C52: REF. A MOV TIT COB DISP 07/01S | D52: 413.4 | E52: 504 | F52: CLIENTES DIVERSOS | G52: 504 | H52: =IFERROR(VLOOKUP(G52&"",PLANO!A:B,2,FALSE),"CONTA NAO EXISTE NO PLANO") | I52: 504 | J52: SEM COSMOS | M52: MOV TIT COB DISP 07/01S
A53: 52 | B53: 07/01/2026 | C53: REF. A PIX ENVIADO GRACIELE APA | D53: -1144 | E53: 187 | F53: SALÁRIOS E ORDENADOS A PAGAR | G53: 187 | H53: =IFERROR(VLOOKUP(G53&"",PLANO!A:B,2,FALSE),"CONTA NAO EXISTE NO PLANO") | I53: 187 | J53: SEM COSMOS | M53: PIX ENVIADO GRACIELE APA
A54: 53 | B54: 07/01/2026 | C54: PIX ENVIADO ALINE DA SIL | D54: -2750 | E54: 506 | F54: FORNECEDORES DIVERSOS | G54: 506 | H54: =IFERROR(VLOOKUP(G54&"",PLANO!A:B,2,FALSE),"CONTA NAO EXISTE NO PLANO") | I54: 506 | J54: SEM COSMOS | M54: PIX ENVIADO ALINE DA SIL
A55: 54 | B55: 07/01/2026 | C55: REF. A PIX ENVIADO LUIZ FELIPE | D55: -1609 | E55: 25 | F55: ADIANTAMENTO DE SALÁRIO | G55: 25 | H55: =IFERROR(VLOOKUP(G55&"",PLANO!A:B,2,FALSE),"CONTA NAO EXISTE NO PLANO") | I55: 25 | J55: SEM COSMOS | M55: PIX ENVIADO LUIZ FELIPE
A56: 55 | B56: 07/01/2026 | C56: FOCUS TECNOLOGIA COMERCIAL QUIMICA LTDAPGTO REF. A COMPRA DE MATERIA PRIMA, COLOREX 5KG,CM50 100KG | D56: -2774.58 | E56: 506 | F56: FORNECEDORES DIVERSOS | G56: 506 | H56: =IFERROR(VLOOKUP(G56&"",PLANO!A:B,2,FALSE),"CONTA NAO EXISTE NO PLANO") | I56: 506 | J56: OK | K56: fornecedor com NF | L56: FOCUS TECNOLOGIA COMERCIAL QUIMICA LTDA | 115/6 | PGTO REF. A COMPRA DE MATERIA PRIMA, COLOREX 5KG, CM50 100KG | M56: FOCUS TECNOLOGIA COMERCIAL QUIMICA LTDA - PGTO REF. A COMPRA DE MATERIA PRIMA, COLOREX 5KG, CM50 100KG
A57: 56 | B57: 07/01/2026 | C57: PIX ENVIADO MARIANE POSS | D57: -1463 | E57: 25 | F57: ADIANTAMENTO DE SALÁRIO | G57: 25 | H57: =IFERROR(VLOOKUP(G57&"",PLANO!A:B,2,FALSE),"CONTA NAO EXISTE NO PLANO") | I57: 25 | J57: SEM COSMOS | M57: PIX ENVIADO MARIANE POSS
A58: 57 | B58: 07/01/2026 | C58: REF. A PIX ENVIADO MARIA FERNAN | D58: -1028 | E58: 25 | F58: ADIANTAMENTO DE SALÁRIO | G58: 25 | H58: =IFERROR(VLOOKUP(G58&"",PLANO!A:B,2,FALSE),"CONTA NAO EXISTE NO PLANO") | I58: 25 | J58: SEM COSMOS | M58: PIX ENVIADO MARIA FERNAN
A59: 58 | B59: 07/01/2026 | C59: REF. A PIX ENVIADO ADRIA FAGUND | D59: -1405 | E59: 25 | F59: ADIANTAMENTO DE SALÁRIO | G59: 25 | H59: =IFERROR(VLOOKUP(G59&"",PLANO!A:B,2,FALSE),"CONTA NAO EXISTE NO PLANO") | I59: 25 | J59: SEM COSMOS | M59: PIX ENVIADO ADRIA FAGUND
A60: 59 | B60: 07/01/2026 | C60: REF. A PIX ENVIADO MARCOS PAULO | D60: -1487 | E60: 511 | F60: FÉRIAS A PAGAR | G60: 511 | H60: =IFERROR(VLOOKUP(G60&"",PLANO!A:B,2,FALSE),"CONTA NAO EXISTE NO PLANO") | I60: 511 | J60: SEM COSMOS | M60: PIX ENVIADO MARCOS PAULO
A61: 60 | B61: 07/01/2026 | C61: REF. A PIX ENVIADO THIAGO TAIT | D61: -1656 | E61: 25 | F61: ADIANTAMENTO DE SALÁRIO | G61: 25 | H61: =IFERROR(VLOOKUP(G61&"",PLANO!A:B,2,FALSE),"CONTA NAO EXISTE NO PLANO") | I61: 25 | J61: SEM COSMOS | M61: PIX ENVIADO THIAGO TAIT
A62: 61 | B62: 07/01/2026 | C62: REF. A PIX ENVIADO BEATRIZ CAMI | D62: -1428 | E62: 25 | F62: ADIANTAMENTO DE SALÁRIO | G62: 25 | H62: =IFERROR(VLOOKUP(G62&"",PLANO!A:B,2,FALSE),"CONTA NAO EXISTE NO PLANO") | I62: 25 | J62: SEM COSMOS | M62: PIX ENVIADO BEATRIZ CAMI
A63: 62 | B63: 07/01/2026 | C63: ALLOXY ESPECIALIDADES QUIMICAS LTDAPGTO REF. A COMPRA DE MATERIA PRIMA, PEROXIDO DEHIDROGENIO | D63: -945 | E63: 56 | F63: MATÉRIA-PRIMA | G63: 506 | H63: =IFERROR(VLOOKUP(G63&"",PLANO!A:B,2,FALSE),"CONTA NAO EXISTE NO PLANO") | I63: 506 | J63: CORRIGIR | K63: fornecedor com NF (Cosmos: compra MP/embalagem) - pagamento deve baixar fornecedores 506 | L63: ALLOXY ESPECIALIDADES QUIMICAS LTDA | 115/6 | PGTO REF. A COMPRA DE MATERIA PRIMA, PEROXIDO DE HIDROGENIO | M63: ALLOXY ESPECIALIDADES QUIMICAS LTDA - PGTO REF. A COMPRA DE MATERIA PRIMA, PEROXIDO DE HIDROGENIO
A64: 63 | B64: 07/01/2026 | C64: RALTER PLASTICOS INDUSTRIA E COMERCIO LTDAPGTO REF. A COMPRA DE TAMPA VERDE | D64: -928.5 | E64: 506 | F64: FORNECEDORES DIVERSOS | G64: 506 | H64: =IFERROR(VLOOKUP(G64&"",PLANO!A:B,2,FALSE),"CONTA NAO EXISTE NO PLANO") | I64: 506 | J64: OK | K64: fornecedor com NF | L64: RALTER PLASTICOS INDUSTRIA E COMERCIO LTDA | 115/9 | PGTO REF. A COMPRA DE TAMPA VERDE | M64: RALTER PLASTICOS INDUSTRIA E COMERCIO LTDA - PGTO REF. A COMPRA DE TAMPA VERDE
A65: 64 | B65: 07/01/2026 | C65: RAPIDO ABC TRANSPORTES LTDAPGTO REF. A FRETE SOBRE COMPRAS | D65: -150 | E65: 312 | F65: FRETES E CARRETOS | G65: 312 | H65: =IFERROR(VLOOKUP(G65&"",PLANO!A:B,2,FALSE),"CONTA NAO EXISTE NO PLANO") | I65: 312 | J65: OK | K65: categoria Cosmos 4 | L65: RAPIDO ABC TRANSPORTES LTDA | 115/4 | PGTO REF. A FRETE SOBRE COMPRAS | M65: RAPIDO ABC TRANSPORTES LTDA - PGTO REF. A FRETE SOBRE COMPRAS
A66: 65 | B66: 07/01/2026 | C66: TNT MERCURIO CARGAS E ENCOMENDAS EXPRESSASPAG REF A FRETE SOBRE VENDAS NF 7471, 7455, 7461,7163 E 7481 | D66: -1080.22 | E66: 312 | F66: FRETES E CARRETOS | G66: 312 | H66: =IFERROR(VLOOKUP(G66&"",PLANO!A:B,2,FALSE),"CONTA NAO EXISTE NO PLANO") | I66: 312 | J66: OK | K66: categoria Cosmos 97 | L66: TNT MERCURIO CARGAS E ENCOMENDAS EXPRESSAS S/A | 115/97 | PAG REF A FRETE SOBRE VENDAS NF 7471, 7455, 7461, 7163 E 7481 | M66: TNT MERCURIO CARGAS E ENCOMENDAS EXPRESSAS S/A - PAG REF A FRETE SOBRE VENDAS NF 7471, 7455, 7461, 7163 E 7481
A67: 66 | B67: 08/01/2026 | C67: REF. A MOV TIT COB DISP 08/01S | D67: 560 | E67: 504 | F67: CLIENTES DIVERSOS | G67: 504 | H67: =IFERROR(VLOOKUP(G67&"",PLANO!A:B,2,FALSE),"CONTA NAO EXISTE NO PLANO") | I67: 504 | J67: SEM COSMOS | M67: MOV TIT COB DISP 08/01S
A68: 67 | B68: 08/01/2026 | C68: REF. A TED 363.0001.RNX F M D R | D68: 13998.58 | E68: 504 | F68: CLIENTES DIVERSOS | G68: 504 | H68: =IFERROR(VLOOKUP(G68&"",PLANO!A:B,2,FALSE),"CONTA NAO EXISTE NO PLANO") | I68: 504 | J68: SEM COSMOS | M68: TED 363.0001.RNX F M D R
A69: 68 | B69: 08/01/2026 | C69: REF. A SISPAG PIX QR-CODE | D69: -182.73 | E69: 555 | F69: INTERNET | G69: 555 | H69: =IFERROR(VLOOKUP(G69&"",PLANO!A:B,2,FALSE),"CONTA NAO EXISTE NO PLANO") | I69: 555 | J69: SEM COSMOS | M69: SISPAG PIX QR-CODE
A70: 69 | B70: 08/01/2026 | C70: M CASSAB COMERCIO E INDUSTRIA LTDAPGTO REF. A COMPRA DE MATERIA PRIMA, TRANSCUTOL 25KG | D70: -2689.85 | E70: 506 | F70: FORNECEDORES DIVERSOS | G70: 506 | H70: =IFERROR(VLOOKUP(G70&"",PLANO!A:B,2,FALSE),"CONTA NAO EXISTE NO PLANO") | I70: 506 | J70: OK | K70: fornecedor com NF | L70: M CASSAB COMERCIO E INDUSTRIA LTDA | 115/6 | PGTO REF. A COMPRA DE MATERIA PRIMA, TRANSCUTOL 25 KG | M70: M CASSAB COMERCIO E INDUSTRIA LTDA - PGTO REF. A COMPRA DE MATERIA PRIMA, TRANSCUTOL 25 KG
A71: 70 | B71: 08/01/2026 | C71: PIX ENVIADO ALINE DA SIL | D71: -6000 | E71: 506 | F71: FORNECEDORES DIVERSOS | G71: 506 | H71: =IFERROR(VLOOKUP(G71&"",PLANO!A:B,2,FALSE),"CONTA NAO EXISTE NO PLANO") | I71: 506 | J71: SEM COSMOS | M71: PIX ENVIADO ALINE DA SIL
A72: 71 | B72: 09/01/2026 | C72: REF. A SISPAG COSMETICON COMER | D72: 10000 | E72: 663 | F72: EMPRESTIMO COSMETICON COMERCIO (31.494.732/0001-09) | G72: 663 | H72: =IFERROR(VLOOKUP(G72&"",PLANO!A:B,2,FALSE),"CONTA NAO EXISTE NO PLANO") | I72: 663 | J72: AJUSTADO | K72: COSMETICON - conta-corrente unica de mutuo (663) | M72: SISPAG COSMETICON COMER
A73: 72 | B73: 09/01/2026 | C73: JULIO CESAR FERREIRA PAGTO REF SERVIÇOS PRESTADOS CONF.CONTRATO | D73: -275 | E73: 362 | F73: SERVIÇOS PRESTADOS POR TERCEIROS | G73: 362 | H73: =IFERROR(VLOOKUP(G73&"",PLANO!A:B,2,FALSE),"CONTA NAO EXISTE NO PLANO") | I73: 362 | J73: OK | K73: servico prestado | L73: JULIO CESAR FERREIRA | 115/172 | PAGTO REF SERVIÇOS PRESTADOS CONF.CONTRATO | M73: JULIO CESAR FERREIRA - PAGTO REF SERVIÇOS PRESTADOS CONF.CONTRATO
A74: 73 | B74: 09/01/2026 | C74: AQIA QUIMICA INOVATIVA LTDA PGTO REF. A COMPRA DE MATERIA PRIMA | D74: -3821.27 | E74: 506 | F74: FORNECEDORES DIVERSOS | G74: 506 | H74: =IFERROR(VLOOKUP(G74&"",PLANO!A:B,2,FALSE),"CONTA NAO EXISTE NO PLANO") | I74: 506 | J74: OK | K74: fornecedor com NF | L74: AQIA QUIMICA INOVATIVA LTDA | 115/6 | PGTO REF. A COMPRA DE MATERIA PRIMA | M74: AQIA QUIMICA INOVATIVA LTDA - PGTO REF. A COMPRA DE MATERIA PRIMA
A75: 74 | B75: 09/01/2026 | C75: BARENTZ BRASIL DISTRIBUIDORA LTDAPGTO REF. A COMPRA DE MATERIA PRIMA BENZOFENONA 4,4KG | D75: -309.79 | E75: 506 | F75: FORNECEDORES DIVERSOS | G75: 506 | H75: =IFERROR(VLOOKUP(G75&"",PLANO!A:B,2,FALSE),"CONTA NAO EXISTE NO PLANO") | I75: 506 | J75: OK | K75: fornecedor com NF | L75: BARENTZ BRASIL DISTRIBUIDORA LTDA | 115/6 | PGTO REF. A COMPRA DE MATERIA PRIMA BENZOFENONA 4, 4KG | M75: BARENTZ BRASIL DISTRIBUIDORA LTDA - PGTO REF. A COMPRA DE MATERIA PRIMA BENZOFENONA 4, 4KG
A76: 75 | B76: 09/01/2026 | C76: INSETCONTROL SERVICOS DE HIGIENE LTDAPGTO REF.PRESTAÇÃO DE SERVIÇOS DE FOCOS PARAINSETOS CONF.EXIGENCIA VIGILÂNCIA | D76: -673.2 | E76: 506 | F76: FORNECEDORES DIVERSOS | G76: 506 | H76: =IFERROR(VLOOKUP(G76&"",PLANO!A:B,2,FALSE),"CONTA NAO EXISTE NO PLANO") | I76: 506 | J76: MANTIDO | K76: servicos diversos (lavanderia, dedetizacao, contabilidade, Plus Sante) | mantida a conta atual (sem informacao que justifique troca) | L76: INSETCONTROL SERVICOS DE HIGIENE LTDA | 115/45 | PGTO REF.PRESTAÇÃO DE SERVIÇOS DE FOCOS PARA INSETOS CONF.EXIGENCIA VIGILÂNCIA | M76: INSETCONTROL SERVICOS DE HIGIENE LTDA - PGTO REF.PRESTAÇÃO DE SERVIÇOS DE FOCOS PARA INSETOS CONF.EXIGENCIA VIGILÂNCIA
A77: 76 | B77: 09/01/2026 | C77: MASTER PUMPS EMBALAGENS COMERCIO IMPORTACAO E EXPORTACAO LTDA PGTO REF. A COMPRA DE EMBALAGEM | D77: -716.99 | E77: 506 | F77: FORNECEDORES DIVERSOS | G77: 506 | H77: =IFERROR(VLOOKUP(G77&"",PLANO!A:B,2,FALSE),"CONTA NAO EXISTE NO PLANO") | I77: 506 | J77: OK | K77: fornecedor com NF | L77: MASTER PUMPS EMBALAGENS COMERCIO IMPORTACAO E EXPORTACAO LTDA | 115/9 | PGTO REF. A COMPRA DE EMBALAGEM | M77: MASTER PUMPS EMBALAGENS COMERCIO IMPORTACAO E EXPORTACAO LTDA - PGTO REF. A COMPRA DE EMBALAGEM
A78: 77 | B78: 09/01/2026 | C78: AZUL LINHAS AEREAS BRASILEIRAS S.A.PGTO REF.FRETE AÉREO PARA VERONICA (CLIENTE CAUCA) | D78: -125.7 | E78: 312 | F78: FRETES E CARRETOS | G78: 312 | H78: =IFERROR(VLOOKUP(G78&"",PLANO!A:B,2,FALSE),"CONTA NAO EXISTE NO PLANO") | I78: 312 | J78: OK | K78: categoria Cosmos 4 | L78: BRASPRESS TRANSPORTES URGENTES LTDA | 115/4 | PAGTO REF FRETE COMPRA CLIENTE VERONICA VENDEDORA CAUCA | M78: BRASPRESS TRANSPORTES URGENTES LTDA - PAGTO REF FRETE COMPRA CLIENTE VERONICA VENDEDORA CAUCA
A79: 78 | B79: 09/01/2026 | C79: QUIMIFORMULA COMERCIO DE PRODUTOS QUIMICOS LTDAPGTO REF. A COMPRA DE MATERIA PRIMA | D79: -1017.95 | E79: 506 | F79: FORNECEDORES DIVERSOS | G79: 506 | H79: =IFERROR(VLOOKUP(G79&"",PLANO!A:B,2,FALSE),"CONTA NAO EXISTE NO PLANO") | I79: 506 | J79: OK | K79: fornecedor com NF | L79: QUIMIFORMULA COMERCIO DE PRODUTOS QUIMICOS LTDA | 115/6 | PGTO REF. A COMPRA DE MATERIA PRIMA | M79: QUIMIFORMULA COMERCIO DE PRODUTOS QUIMICOS LTDA - PGTO REF. A COMPRA DE MATERIA PRIMA
A80: 79 | B80: 09/01/2026 | C80: SAVATEC COMERCIO E SERVICOS LTDAPGTO REF. A COMPRA DE MATERIAL PARA LABORATORIO | D80: -990.61 | E80: 359 | F80: MATERIAL DE ESCRITÓRIO | G80: 359 | H80: =IFERROR(VLOOKUP(G80&"",PLANO!A:B,2,FALSE),"CONTA NAO EXISTE NO PLANO") | I80: 359 | J80: MANTIDO | K80: material laboratorio/embalagem consumo | mantida a conta atual (sem informacao que justifique troca) | L80: SAVATEC COMERCIO E SERVICOS LTDA | 115/8 | PGTO REF. A COMPRA DE MATERIAL PARA LABORATORIO | M80: SAVATEC COMERCIO E SERVICOS LTDA - PGTO REF. A COMPRA DE MATERIAL PARA LABORATORIO
A81: 80 | B81: 09/01/2026 | C81: SAVATEC COMERCIO E SERVICOS LTDAPGTO REF. A COMPRA DE MATERIAL PARA LABORATORIO | D81: -588.45 | E81: 359 | F81: MATERIAL DE ESCRITÓRIO | G81: 359 | H81: =IFERROR(VLOOKUP(G81&"",PLANO!A:B,2,FALSE),"CONTA NAO EXISTE NO PLANO") | I81: 359 | J81: MANTIDO | K81: material laboratorio/embalagem consumo | mantida a conta atual (sem informacao que justifique troca) | L81: SAVATEC COMERCIO E SERVICOS LTDA | 115/8 | PGTO REF. A COMPRA DE MATERIAL PARA LABORATORIO | M81: SAVATEC COMERCIO E SERVICOS LTDA - PGTO REF. A COMPRA DE MATERIAL PARA LABORATORIO
A82: 81 | B82: 09/01/2026 | C82: BRASPRESS TRANSPORTES URGENTES LTDAPGTO REF.FRETE | D82: -442.59 | E82: 312 | F82: FRETES E CARRETOS | G82: 312 | H82: =IFERROR(VLOOKUP(G82&"",PLANO!A:B,2,FALSE),"CONTA NAO EXISTE NO PLANO") | I82: 312 | J82: OK | K82: categoria Cosmos 97 | L82: BRASPRESS TRANSPORTES URGENTES LTDA | 115/97 | PGTO REF.FRETE | M82: BRASPRESS TRANSPORTES URGENTES LTDA - PGTO REF.FRETE
A83: 82 | B83: 09/01/2026 | C83: OXXYGENIO SITIOPGTO REF. A 2 CILINDROS DE NITROGENIO | D83: -520 | E83: 506 | F83: FORNECEDORES DIVERSOS | G83: 506 | H83: =IFERROR(VLOOKUP(G83&"",PLANO!A:B,2,FALSE),"CONTA NAO EXISTE NO PLANO") | I83: 506 | J83: MANTIDO | K83: nitrogenio/materiais | mantida a conta atual (sem informacao que justifique troca) | L83: OXXYGENIO SITIO | 115/104 | PGTO REF. A 2 CILINDROS DE NITROGENIO | M83: OXXYGENIO SITIO - PGTO REF. A 2 CILINDROS DE NITROGENIO
A84: 83 | B84: 12/01/2026 | C84: COPEL DISTRIBUICAO S.APGTO REF.DISTRIBUIÇÃO E CONSUMO DE ENERGIA | D84: -3954.29 | E84: 354 | F84: ENERGIA ELÉTRICA | G84: 354 | H84: =IFERROR(VLOOKUP(G84&"",PLANO!A:B,2,FALSE),"CONTA NAO EXISTE NO PLANO") | I84: 354 | J84: OK | K84: categoria Cosmos 13 | L84: COPEL DISTRIBUICAO S.A. | 115/13 | PGTO REF.DISTRIBUIÇÃO E CONSUMO DE ENERGIA | M84: COPEL DISTRIBUICAO S.A. - PGTO REF.DISTRIBUIÇÃO E CONSUMO DE ENERGIA
... A98: 97 | B98: 13/01/2026 | C98: BARENTZ BRASIL DISTRIBUIDORA LTDAPGTO REF. A COMPRA DE MATERIA PRIMA BENZOFENONA 4,4KG | D98: -306.73 | E98: 506 | F98: FORNECEDORES DIVERSOS | G98: 506 | H98: =IFERROR(VLOOKUP(G98&"",PLANO!A:B,2,FALSE),"CONTA NAO EXISTE NO PLANO") | I98: 506 | J98: OK | K98: fornecedor com NF | L98: BARENTZ BRASIL DISTRIBUIDORA LTDA | 115/6 | PGTO REF. A COMPRA DE MATERIA PRIMA BENZOFENONA 4, 4KG | M98: BARENTZ BRASIL DISTRIBUIDORA LTDA - PGTO REF. A COMPRA DE MATERIA PRIMA BENZOFENONA 4, 4KG
A99: 98 | B99: 13/01/2026 | C99: REF. A BOLETO PAGO E. J. KRIEGE | D99: -509.16 | E99: 506 | F99: FORNECEDORES DIVERSOS | G99: 506 | H99: =IFERROR(VLOOKUP(G99&"",PLANO!A:B,2,FALSE),"CONTA NAO EXISTE NO PLANO") | I99: 506 | J99: SEM COSMOS | M99: BOLETO PAGO E. J. KRIEGE
A100: 99 | B100: 13/01/2026 | C100: REAGEN PRODUTOS PARA LABORATORIOS EIRELI PGTO REF. A COMPRA DE MATERIAL PATRA LABORATÓRIO | D100: -202.67 | E100: 506 | F100: FORNECEDORES DIVERSOS | G100: 506 | H100: =IFERROR(VLOOKUP(G100&"",PLANO!A:B,2,FALSE),"CONTA NAO EXISTE NO PLANO") | I100: 506 | J100: MANTIDO | K100: material laboratorio/contratipagem | mantida a conta atual (sem informacao que justifique troca) | L100: REAGEN PRODUTOS PARA LABORATORIOS EIRELI | 115/103 | PGTO REF. A COMPRA DE MATERIAL PATRA LABORATÓRIO | M100: REAGEN PRODUTOS PARA LABORATORIOS EIRELI - PGTO REF. A COMPRA DE MATERIAL PATRA LABORATÓRIO
A101: 100 | B101: 13/01/2026 | C101: YAHWEH PRINT BRASIL LTDAPGTO REF. A COMPRA DE ROTULO MASCARA CELULA TRONCO | D101: -1030.24 | E101: 506 | F101: FORNECEDORES DIVERSOS | G101: 506 | H101: =IFERROR(VLOOKUP(G101&"",PLANO!A:B,2,FALSE),"CONTA NAO EXISTE NO PLANO") | I101: 506 | J101: OK | K101: fornecedor com NF | L101: YAHWEH PRINT BRASIL LTDA | 115/9 | PGTO REF. A COMPRA DE ROTULO MASCARA CELULA TRONCO | M101: YAHWEH PRINT BRASIL LTDA - PGTO REF. A COMPRA DE ROTULO MASCARA CELULA TRONCO
A102: 101 | B102: 13/01/2026 | C102: YAHWEH PRINT BRASIL LTDAPGTO REF. A COMPRA DE ROTULO | D102: -1329.18 | E102: 506 | F102: FORNECEDORES DIVERSOS | G102: 506 | H102: =IFERROR(VLOOKUP(G102&"",PLANO!A:B,2,FALSE),"CONTA NAO EXISTE NO PLANO") | I102: 506 | J102: OK | K102: fornecedor com NF | L102: YAHWEH PRINT BRASIL LTDA | 115/9 | PGTO REF. A COMPRA DE ROTULO | M102: YAHWEH PRINT BRASIL LTDA - PGTO REF. A COMPRA DE ROTULO
A103: 102 | B103: 14/01/2026 | C103: REF. A SISPAG COSMETICON COMER (OUTRAS ENTRADAS) | D103: 15000 | E103: 663 | F103: EMPRESTIMO COSMETICON COMERCIO (31.494.732/0001-09) | G103: 663 | H103: =IFERROR(VLOOKUP(G103&"",PLANO!A:B,2,FALSE),"CONTA NAO EXISTE NO PLANO") | I103: 663 | J103: AJUSTADO | K103: COSMETICON - conta-corrente unica de mutuo (663) | L103: OUTRAS ENTRADAS | 122/71 | | M103: SISPAG COSMETICON COMER (OUTRAS ENTRADAS)
A104: 103 | B104: 14/01/2026 | C104: REF. A MOV TIT COB DISP 14/01S | D104: 5444.32 | E104: 504 | F104: CLIENTES DIVERSOS | G104: 504 | H104: =IFERROR(VLOOKUP(G104&"",PLANO!A:B,2,FALSE),"CONTA NAO EXISTE NO PLANO") | I104: 504 | J104: SEM COSMOS | M104: MOV TIT COB DISP 14/01S
A105: 104 | B105: 14/01/2026 | C105: FLASH TECNOLOGIA E INSTITUICAO DE PAGAMENTO LTDAPGTO REF. COMPRA VALE ALIMENTACAO | D105: -8070 | E105: 555 | F105: INTERNET | G105: 659 | H105: =IFERROR(VLOOKUP(G105&"",PLANO!A:B,2,FALSE),"CONTA NAO EXISTE NO PLANO") | I105: 659 | J105: CORRIGIR | K105: categoria Cosmos 34 | L105: FLASH TECNOLOGIA E INSTITUICAO DE PAGAMENTO LTDA | 115/34 | PGTO REF. COMPRA VALE ALIMENTACAO | M105: FLASH TECNOLOGIA E INSTITUICAO DE PAGAMENTO LTDA - PGTO REF. COMPRA VALE ALIMENTACAO
A106: 105 | B106: 14/01/2026 | C106: PIX ENVIADO ALINE DA SIL | D106: -2350 | E106: 506 | F106: FORNECEDORES DIVERSOS | G106: 506 | H106: =IFERROR(VLOOKUP(G106&"",PLANO!A:B,2,FALSE),"CONTA NAO EXISTE NO PLANO") | I106: 506 | J106: SEM COSMOS | M106: PIX ENVIADO ALINE DA SIL
A107: 106 | B107: 14/01/2026 | C107: BRAL-MAX INDUSTRIA E COMERCIO DE PLASTICOS LTDA PAGAMENTO REFERENTE A COMPRA DE TAMPA ROSCA PRATAE NATURAL | D107: -1417.64 | E107: 506 | F107: FORNECEDORES DIVERSOS | G107: 506 | H107: =IFERROR(VLOOKUP(G107&"",PLANO!A:B,2,FALSE),"CONTA NAO EXISTE NO PLANO") | I107: 506 | J107: OK | K107: fornecedor com NF | L107: BRAL MAX INDUSTRIA E COMERCIO DE PLASTICOS LTDA | 115/9 | PAGAMENTO REFERENTE A COMPRA DE TAMPA ROSCA PRATA E NATURAL | M107: BRAL MAX INDUSTRIA E COMERCIO DE PLASTICOS LTDA - PAGAMENTO REFERENTE A COMPRA DE TAMPA ROSCA PRATA E NATURAL
A108: 107 | B108: 14/01/2026 | C108: BEATRIZ CAMILA MARCELINO DOS SANTOS PGTO REF. A VALE ALIMENTAÇÃO | D108: -555 | E108: 659 | F108: VA / VR | G108: 659 | H108: =IFERROR(VLOOKUP(G108&"",PLANO!A:B,2,FALSE),"CONTA NAO EXISTE NO PLANO") | I108: 659 | J108: OK | K108: categoria Cosmos 93 | L108: BEATRIZ CAMILA MARCELINO DOS SANTOS | 115/93 | PGTO REF. A VALE ALIMENTAÇÃO | M108: BEATRIZ CAMILA MARCELINO DOS SANTOS - PGTO REF. A VALE ALIMENTAÇÃO
A109: 108 | B109: 14/01/2026 | C109: ALLOXY ESPECIALIDADES QUIMICAS LTDA PGTO REF. A COMPRA DE MATERIA PRIMA, PEROXIDO DEHIDROGENIO | D109: -945 | E109: 56 | F109: MATÉRIA-PRIMA | G109: 506 | H109: =IFERROR(VLOOKUP(G109&"",PLANO!A:B,2,FALSE),"CONTA NAO EXISTE NO PLANO") | I109: 506 | J109: CORRIGIR | K109: fornecedor com NF (Cosmos: compra MP/embalagem) - pagamento deve baixar fornecedores 506 | L109: ALLOXY ESPECIALIDADES QUIMICAS LTDA | 115/6 | PGTO REF. A COMPRA DE MATERIA PRIMA, PEROXIDO DE HIDROGENIO | M109: ALLOXY ESPECIALIDADES QUIMICAS LTDA - PGTO REF. A COMPRA DE MATERIA PRIMA, PEROXIDO DE HIDROGENIO
A110: 109 | B110: 14/01/2026 | C110: PERMUTION MULTI SERVIÇOS E DISTRIBUIDORA LTDA PGTO REF. A COMPRA DE RESINA CATIONICA E CARVÃOATIVADO PARA TRATAMENTO DE ÁGUA | D110: -1107.58 | E110: 506 | F110: FORNECEDORES DIVERSOS | G110: 58 | H110: =IFERROR(VLOOKUP(G110&"",PLANO!A:B,2,FALSE),"CONTA NAO EXISTE NO PLANO") | I110: 506 | J110: AJUSTADO | K110: material de consumo industrial (filtro, resina, lenha caldeira) | L110: PERMUTION MULTI SERVIÇOS E DISTRIBUIDORA LTDA | 115/16 | PGTO REF. A COMPRA DE RESINA CATIONICA E CARVÃO ATIVADO PARA TRATAMENTO DE ÁGUA | M110: PERMUTION MULTI SERVIÇOS E DISTRIBUIDORA LTDA - PGTO REF. A COMPRA DE RESINA CATIONICA E CARVÃO ATIVADO PARA TRATAMENTO DE ÁGUA
A111: 110 | B111: 14/01/2026 | C111: INDUSTRIA QUIMICA ANASTACIO S A PGTO REF. A COMPRA DE MATERIA PRIMA, VASELINASOLIDA 340 KG, ERITORBATO DE SODIO 25 KG | D111: -1928.78 | E111: 506 | F111: FORNECEDORES DIVERSOS | G111: 506 | H111: =IFERROR(VLOOKUP(G111&"",PLANO!A:B,2,FALSE),"CONTA NAO EXISTE NO PLANO") | I111: 506 | J111: OK | K111: fornecedor com NF | L111: INDUSTRIA QUIMICA ANASTACIO S A | 115/6 | PGTO REF. A COMPRA DE MATERIA PRIMA, VASELINA SOLIDA 340 KG, ERITORBATO DE SODIO 25 KG | M111: INDUSTRIA QUIMICA ANASTACIO S A - PGTO REF. A COMPRA DE MATERIA PRIMA, VASELINA SOLIDA 340 KG, ERITORBATO DE SODIO
A112: 111 | B112: 14/01/2026 | C112: MULTIQUIM INDUSTRIA COMERCIO IMPORTACAO E EXP LTDAPGTO REF. A COMPRA DE ACIDO TIOGLICOLICO 160 KG | D112: -5317.4 | E112: 506 | F112: FORNECEDORES DIVERSOS | G112: 506 | H112: =IFERROR(VLOOKUP(G112&"",PLANO!A:B,2,FALSE),"CONTA NAO EXISTE NO PLANO") | I112: 506 | J112: OK | K112: fornecedor com NF | L112: MULTIQUIM INDUSTRIA COMERCIO IMPORTACAO E EXP LTDA | 115/97 | PGTO REF. A COMPRA DE ACIDO TIOGLICOLICO 160 KG | M112: MULTIQUIM INDUSTRIA COMERCIO IMPORTACAO E EXP LTDA - PGTO REF. A COMPRA DE ACIDO TIOGLICOLICO 160 KG
A113: 112 | B113: 15/01/2026 | C113: REF. A TED 363.0001.RNX F M D R | D113: 3633.7 | E113: 504 | F113: CLIENTES DIVERSOS | G113: 504 | H113: =IFERROR(VLOOKUP(G113&"",PLANO!A:B,2,FALSE),"CONTA NAO EXISTE NO PLANO") | I113: 504 | J113: SEM COSMOS | M113: TED 363.0001.RNX F M D R
...

Sheet CONCILIACAO
A1: Mês | B1: Saldo inicial | C1: Entradas | D1: Saídas | E1: Saldo final calculado | F1: Saldo final extrato Itaú (C/C + aplicação) | G1: Diferença
A2: 01/2026 | B2: -32080.74 | C2: 281856.26 | D2: 253690.61 | E2: -3915.09 | F2: -3915.09 | G2: 0
A3: 02/2026 | B3: -3915.09 | C3: 265354.61 | D3: 299973.24 | E3: -38533.72 | F3: -38533.72 | G3: 0
A4: 03/2026 | B4: -38533.72 | C4: 313465.79 | D4: 296848.4 | E4: -21916.33 | F4: -21916.33 | G4: 0
A5: 04/2026 | B5: -21916.33 | C5: 392720.26 | D5: 368317.92 | E5: 2486.01 | F5: 2486.01 | G5: 0
A6: 05/2026 | B6: 2486.01 | C6: 387063.37 | D6: 398069.43 | E6: -8520.05 | F6: -8520.05 | G6: 0
A7: 06/2026 | B7: -8520.05 | C7: 316039 | D7: 308773.88 | E7: -1254.93 | F7: -1254.93 | G7: 0
A8: 07/2026 | B8: -1254.93 | C8: 389184.94 | D8: 379543.75 | E8: 8386.26 | F8: 8386.26 | G8: 0
A9: 08/2026 | B9: 8386.26 | C9: 368170.45 | D9: 380062.8 | E9: -3506.09 | F9: -3506.09 | G9: 0

Sheet EMPRESAS DO GRUPO
A1: Empresa | B1: Mês | C1: Entradas (recebido) | D1: Saídas (enviado) | E1: Líquido | F1: Contas usadas hoje
A2: CABELO MEU | B2: 06/2026 | C2: 0 | D2: 328.09 | E2: -328.09 | F2: 506
A3: COSMETICON | B3: 01/2026 | C3: 131000 | D3: 0 | E3: 131000 | F3: 663
A4: COSMETICON | B4: 02/2026 | C4: 36000 | D4: 2000 | E4: 34000 | F4: 663, 664
A5: COSMETICON | B5: 03/2026 | C5: 25000 | D5: 13700 | E5: 11300 | F5: 663, 664
A6: COSMETICON | B6: 04/2026 | C6: 5800 | D6: 93600 | E6: -87800 | F6: 663, 664
A7: COSMETICON | B7: 05/2026 | C7: 0 | D7: 51000 | E7: -51000 | F7: 361, 664
A8: COSMETICON | B8: 06/2026 | C8: 3000 | D8: 12500 | E8: -9500 | F8: 361, 506, 663, 664
A9: COSMETICON | B9: 07/2026 | C9: 3000 | D9: 1000 | E9: 2000 | F9: 663
A10: COSMETICON | B10: 08/2026 | C10: 18600 | D10: 11000 | E10: 7600 | F10: 663
A11: F.V.S | B11: 03/2026 | C11: 0 | D11: 4000 | E11: -4000 | F11: 671
A12: F.V.S | B12: 04/2026 | C12: 3100 | D12: 5200 | E12: -2100 | F12: 662, 671
A13: F.V.S | B13: 05/2026 | C13: 0 | D13: 2000 | E13: -2000 | F13: 671
... A24: GULA/FIQUE BEM/FIQUE BEM | B24: 08/2026 | C24: 0 | D24: 72000 | E24: -72000 | F24: 366
A26: Sugestão (decidir): uma conta-corrente de mútuo por empresa do grupo, usada tanto na entrada quanto na saída -> COSMETICON 663, F.V.S 662, CABELO MEU 670, GULA/FIQUE BEM sem conta própria (672 EMPRESTIMO DE TERCEIRO ou criar conta). Recebimento de NOTA de venda dessas empresas continua baixando o cliente (664/671).

Sheet PLANO
A1: 1 | B1: ATIVO
A2: 2 | B2: ATIVO CIRCULANTE
A3: 3 | B3: DISPONÍVEL
A4: 4 | B4: CAIXA
A5: 5 | B5: CAIXA GERAL
A6: 7 | B6: BANCOS CONTA MOVIMENTO
A7: 8 | B7: ITAU EMPRESAS - CONTA 53570-0
A8: 9 | B8: ITAU EMPRESAS - GARANTIDA C/C 52508-1
A9: 10 | B9: APLICAÇÕES FINANCEIRAS LIQUIDEZ IMEDIATA
A10: 11 | B10: APLICAÇÃO ITAU
A11: 12 | B11: CLIENTES
A12: 13 | B12: DUPLICATAS A RECEBER
... A200: 715 | B200: HONORARIOS ADVCATICIOS
