Workbook

Sheet Resumo
A1: KORP Filial (145) - Fechamento da folha - Contas patrimoniais
A2: Valores = movimento do mês (crédito - débito). Confere = folha do mês + competência de outros meses = TXT corrigido.
A4: Conta | B4: Descrição | C4: 08-2026
A5: 2521 | B5: Salários a Pagar | C5: ='08-2026'!F5
A6: 2523 | B6: Indenizações Trabalhistas (rescisões) | C6: ='08-2026'!F6
A7: 2524 | B7: Férias a Pagar | C7: ='08-2026'!F7
A8: 2526 | B8: Estágios a pagar | C8: ='08-2026'!F8
A9: 2530 | B9: FGTS a Recolher | C9: ='08-2026'!F9
A10: 2531 | B10: INSS a Recolher | C10: ='08-2026'!F10
A11: 2533 | B11: IRRF a Recolher s/ Folha | C11: ='08-2026'!F11
A12: 3137 | B12: Empréstimo a Funcionário (consignado) | C12: ='08-2026'!F12
A13: 2463 | B13: Adiantamento de Férias (ativo) | C13: ='08-2026'!F13
B14: Confere com a folha? | C14: =IF(COUNTIF('08-2026'!H5:H13,"Não")=0,"Sim","Não")

Sheet 08-2026
A1: KORP Filial (145) - Fechamento da folha - Contas patrimoniais - 08/2026
A2: Folha 08/2026. Outros meses no TXT de 08: rescisão de estágio da Isabele (07); parte das férias do Matheus e da Ana de 09 (férias pagas integralmente em 08); férias da Fernanda lançadas no TXT de 07. Faltam no TXT de 08: rescisões de Guilherme, Enzo e Wellington (devem vir no TXT de 09). Consignado da Ana: estorno e provisão excluídos (confirmado).
A4: Conta | B4: Descrição | C4: Valor pela folha (extrato do mês) | D4: Valor no TXT do Domínio | E4: Correções de conta | F4: TXT corrigido (lançado na Korp) | G4: Competência de outros meses no TXT | H4: Confere? | I4: Composição
A5: 2521 | B5: Salários a Pagar | C5: 74358.67 | D5: 81670.02 | E5: -7311.35 | F5: =D5+E5 | G5: 0 | H5: =IF(ABS(C5+G5-F5)<1,"Sim","Não") | I5: Correções: -3.800,00 e -3.900,00 bolsas (CC 7 e 13) para 2526; +3.339,00 salário do Bruno com D/C na mesma conta; -3.329,46 verbas e descontos da rescisão Alyson/Wendel para 2523; +1.730,46 afastamento invertido (CC 8); +94,98 diferença de férias da Fernanda; +2,62 horas extras Isabele; -70,00 contribuição do CC 14 invertida; -1.378,95 consignado da Ana (exclusão do estorno 459,65 e da provisão 919,30)
A6: 2523 | B6: Indenizações Trabalhistas (rescisões) | C6: 35826.55 | D6: -258.79 | E6: 11384.54 | F6: =D6+E6 | G6: -24700.8 | H6: =IF(ABS(C6+G6-F6)<1,"Sim","Não") | I6: Folha = líquido das 5 rescisões de 08. Correções: verbas e descontos da rescisão Alyson/Wendel para 2523 (fica 11.125,75). Outros meses: -24.700,80 rescisões de Guilherme 9.151,01, Enzo 6.958,54 e Wellington 8.591,25 (TXT de 09)
A7: 2524 | B7: Férias a Pagar | C7: 272.15 | D7: 16071.07 | E7: -13551.34 | F7: =D7+E7 | G7: 2247.58 | H7: =IF(ABS(C7+G7-F7)<1,"Sim","Não") | I7: Correções: -5.278,74 verbas da rescisão Alyson/Wendel para 2523; -7.741,67 adiantamentos de férias (Matheus, Ana, Fernanda) não exportados; -433,33 bolsa férias Isabele para 2526; -94,98 diferença de férias Fernanda e -2,62 horas extras Isabele para 2521. Outros meses: +1.534,30 férias do Matheus e +2.467,96 da Ana referentes a 09; -1.754,68 férias da Fernanda lançadas no TXT de 07
A8: 2526 | B8: Estágios a pagar | C8: 9587.1 | D8: 3187.1 | E8: 8133.33 | F8: =D8+E8 | G8: 1733.33 | H8: =IF(ABS(C8+G8-F8)<1,"Sim","Não") | I8: Correções: +3.800,00, +3.900,00 bolsas e +433,33 bolsa férias Isabele. Outros meses: +1.733,33 rescisão de estágio da Isabele (competência 07)
A9: 2530 | B9: FGTS a Recolher | C9: 12857.16 | D9: 8348.98 | E9: 253.99 | F9: =D9+E9 | G9: -4254.19 | H9: =IF(ABS(C9+G9-F9)<1,"Sim","Não") | I9: Folha = Valor do FGTS 8.330,01 + FGTS rescisório 4.527,15. Correção: +253,99 FGTS de aviso prévio creditado em IRRF. Outros meses: -4.254,19 FGTS das rescisões de Guilherme 1.669,39, Enzo 1.988,87 e Wellington 595,93 (TXT de 09)
A10: 2531 | B10: INSS a Recolher | C10: 40437.54 | D10: 39798.67 | E10: 0 | F10: =D10+E10 | G10: -638.3 | H10: =IF(ABS(C10+G10-F10)<1,"Sim","Não") | I10: Outros meses: -1.023,65 INSS das rescisões de 09 (Guilherme, Enzo, Wellington); +532,16 INSS férias de 09 (Matheus 223,90; Ana 308,26); -146,81 INSS férias Fernanda (TXT de 07). Diferença de 0,57 = arredondamento
A11: 2533 | B11: IRRF a Recolher s/ Folha | C11: 2237.82 | D11: 2866.42 | E11: -253.99 | F11: =D11+E11 | G11: 374.61 | H11: =IF(ABS(C11+G11-F11)<1,"Sim","Não") | I11: Correção: -253,99 FGTS de aviso prévio lançado em IRRF. Outros meses: +374,61 IRRF férias de 09 (Matheus 228,13; Ana 146,48)
A12: 3137 | B12: Empréstimo a Funcionário (consignado) | C12: 3811.33 | D12: 15.67 | E12: 1378.95 | F12: =D12+E12 | G12: -2416.71 | H12: =IF(ABS(C12+G12-F12)<1,"Sim","Não") | I12: Folha = Ana 919,30 + Jhonatan 475,32 + Enzo (rescisão) 2.416,71. Correção: +1.378,95 exclusão do estorno 459,65 e da provisão 919,30 do consignado da Ana (confirmado). Outros meses: -2.416,71 consignado da rescisão do Enzo (TXT de 09)
A13: 2463 | B13: Adiantamento de Férias (ativo) | C13: 7741.67 | D13: 0 | E13: 7741.67 | F13: =D13+E13 | G13: 0 | H13: =IF(ABS(C13+G13-F13)<1,"Sim","Não") | I13: Correção: +7.741,67 baixa dos adiantamentos de férias (Matheus 4.063,10; Ana 1.923,89; Fernanda 1.754,68) não exportados
A15: Salários + Indenizações + Férias + Estágios a pagar
B16: Total | C16: =C5+C6+C7+C8 | D16: =D5+D6+D7+D8 | F16: =F5+F6+F7+F8 | G16: =G5+G6+G7+G8
