Workbook

Sheet Comparativo
B2: KOPP INDÚSTRIA — Lucro Presumido x Simples Nacional
B3: Mesmo faturamento de jan a set/2026 · CNPJ 02.967.738/0001-58 · Domínio 60
B5: FATURAMENTO | C5: LUCRO PRESUMIDO | D5: SIMPLES (DAS) | E5: DIFERENÇA
B6: ='Detalhe mensal'!B14 | C6: ='Detalhe mensal'!L14 | D6: ='Detalhe mensal'!N14 | E6: =ABS('Detalhe mensal'!P14)
B7: jan a set/2026 | C7: ='Detalhe mensal'!M14 | D7: ='Detalhe mensal'!O14 | E7: =IF('Detalhe mensal'!P14>0,"o Simples custaria a mais","o Simples economizaria")
B9: Com o faturamento de 2026, o Lucro Presumido saiu R$ 150.804,35 mais barato que o Simples Nacional.
B11: Trimestre | C11: Faturamento | D11: Lucro Presumido | E11: Simples (DAS) | F11: Simples − Presumido
B12: 1º trimestre | C12: =SUM('Detalhe mensal'!B5:B7) | D12: =SUM('Detalhe mensal'!L5:L7) | E12: =SUM('Detalhe mensal'!N5:N7) | F12: =E12-D12
B13: 2º trimestre | C13: =SUM('Detalhe mensal'!B8:B10) | D13: =SUM('Detalhe mensal'!L8:L10) | E13: =SUM('Detalhe mensal'!N8:N10) | F13: =E13-D13
B14: 3º trimestre | C14: =SUM('Detalhe mensal'!B11:B13) | D14: =SUM('Detalhe mensal'!L11:L13) | E14: =SUM('Detalhe mensal'!N11:N13) | F14: =E14-D14
B15: Total | C15: =SUM(C12:C14) | D15: =SUM(D12:D14) | E15: =SUM(E12:E14) | F15: =SUM(F12:F14)
B33: Observações
B34: • Presumido = PIS + COFINS + IRPJ + CSLL + ICMS + IPI + DIFAL não contribuinte + diferencial de alíquota + ICMS antecipado.
B35: • Simples = DAS simulado no Domínio com o mesmo faturamento.
B36: • ICMS e IPI no Presumido ficaram zerados pelos créditos das compras (saldo credor). No Simples esses créditos se perdem.
B37: • A contribuição patronal ao INSS (CPP) da folha não está somada no Presumido. No Simples (Anexo II), ela já vem dentro do DAS.
B38: • Mesmo que toda a GPS/DCTFWeb de jan a ago (R$ 62.974,80, incluindo a parte dos empregados) fosse somada ao Presumido, ele continuaria mais barato.
B39: • Ficaram fora apenas as retenções de impostos de terceiros (IRRF, CSRF e ISS retidos) — ver aba "Fora da comparação".

Sheet Detalhe mensal
A1: Detalhe mensal — Lucro Presumido x Simples Nacional (jan a set/2026)
A2: Fontes: Relatório de Faturamento, Resumo dos Impostos (empresa 60) e simulação do DAS (empresa 2000) — Domínio, emitidos em 14/10/2026
A4: Mês | B4: Faturamento | C4: PIS | D4: COFINS | E4: IRPJ | F4: CSLL | G4: ICMS | H4: IPI | I4: DIFAL não contribuinte | J4: Diferencial de alíquota (compras) | K4: ICMS antecipado | L4: Total Presumido | M4: % s/ fat. | N4: DAS Simples | O4: % s/ fat. | P4: Diferença (Simples − Presumido)
A5: Jan/26 | B5: 122255.79 | C5: 17.59 | D5: 81.19 | E5: 0 | F5: 0 | G5: 0 | H5: 0 | I5: 41.84 | J5: 122.52 | K5: 456.71 | L5: =SUM(C5:K5) | M5: =L5/B5 | N5: 14719.75 | O5: =N5/B5 | P5: =N5-L5
A6: Fev/26 | B6: 220115.95 | C6: 42.33 | D6: 195.39 | E6: 0 | F6: 0 | G6: 0 | H6: 0 | I6: 86.55 | J6: 197.71 | K6: 0 | L6: =SUM(C6:K6) | M6: =L6/B6 | N6: 26267.9 | O6: =N6/B6 | P6: =N6-L6
A7: Mar/26 | B7: 301153.81 | C7: 90.84 | D7: 419.26 | E7: 7723.87 | F7: 6951.71 | G7: 0 | H7: 0 | I7: 179.43 | J7: 203.45 | K7: 4153.42 | L7: =SUM(C7:K7) | M7: =L7/B7 | N7: 35977.34 | O7: =N7/B7 | P7: =N7-L7
A8: Abr/26 | B8: 229521.7 | C8: 222.56 | D8: 1027.21 | E8: 0 | F8: 0 | G8: 0 | H8: 0 | I8: 45.69 | J8: 841.41 | K8: 191.92 | L8: =SUM(C8:K8) | M8: =L8/B8 | N8: 27304.5 | O8: =N8/B8 | P8: =N8-L8
A9: Mai/26 | B9: 269324.11 | C9: 295.66 | D9: 1364.76 | E9: 0 | F9: 0 | G9: 0 | H9: 0 | I9: 642.07 | J9: 58.23 | K9: 2692.26 | L9: =SUM(C9:K9) | M9: =L9/B9 | N9: 31964.84 | O9: =N9/B9 | P9: =N9-L9
A10: Jun/26 | B10: 113054.22 | C10: 200 | D10: 923.37 | E10: 7369.98 | F10: 6625.9 | G10: 0 | H10: 0 | I10: 318.67 | J10: 0 | K10: 6.39 | L10: =SUM(C10:K10) | M10: =L10/B10 | N10: 13459.6 | O10: =N10/B10 | P10: =N10-L10
A11: Jul/26 | B11: 252256.51 | C11: 213.99 | D11: 987.79 | E11: 0 | F11: 0 | G11: 0 | H11: 0 | I11: 56.89 | J11: 0 | K11: 2216.43 | L11: =SUM(C11:K11) | M11: =L11/B11 | N11: 29568.19 | O11: =N11/B11 | P11: =N11-L11
A12: Ago/26 | B12: 97406.59 | C12: 219.76 | D12: 1014.66 | E12: 0 | F12: 0 | G12: 0 | H12: 0 | I12: 0 | J12: 299.76 | K12: 1933.41 | L12: =SUM(C12:K12) | M12: =L12/B12 | N12: 11422.98 | O12: =N12/B12 | P12: =N12-L12
A13: Set/26 | B13: 225407.76 | C13: 246.9 | D13: 1139.82 | E13: 6802.18 | F13: 6325.26 | G13: 0 | H13: 0 | I13: 423.5 | J13: 167.7 | K13: 0 | L13: =SUM(C13:K13) | M13: =L13/B13 | N13: 25957.19 | O13: =N13/B13 | P13: =N13-L13
A14: Total | B14: =SUM(B5:B13) | C14: =SUM(C5:C13) | D14: =SUM(D5:D13) | E14: =SUM(E5:E13) | F14: =SUM(F5:F13) | G14: =SUM(G5:G13) | H14: =SUM(H5:H13) | I14: =SUM(I5:I13) | ... L14: =SUM(L5:L13) | M14: =L14/B14 | N14: =SUM(N5:N13) | O14: =N14/B14 | P14: =SUM(P5:P13)
A16: IRPJ e CSLL do Presumido são trimestrais: aparecem em março, junho e setembro (apuração do trimestre).
A17: ICMS e IPI ficaram com saldo credor em todos os meses (nada a recolher). Saldo credor em 30/09/2026: ICMS R$ 3.553,33 · IPI R$ 7.810,94 — esses créditos não são aproveitados no Simples.

Sheet Fora da comparação
A1: Valores que NÃO entram no comparativo
A2: São retenções de impostos de terceiros (prestadores de serviço): a Kopp só repassa, não é custo dela.
A4: Item | B4: Jan/26 | C4: Fev/26 | D4: Mar/26 | E4: Abr/26 | F4: Mai/26 | G4: Jun/26 | H4: Jul/26 | I4: Ago/26 | J4: Set/26 | K4: Total
A5: IRRF retido de terceiros | B5: 55.45 | C5: 68.49 | D5: 85.95 | E5: 174.79 | F5: 179.01 | G5: 316.09 | H5: 162.57 | I5: 162.58 | J5: 207.36 | K5: =SUM(B5:J5)
A6: CSRF retida de terceiros | B6: 219.4 | C6: 231.11 | D6: 330.11 | E6: 505.27 | F6: 594.45 | G6: 937.12 | H6: 522.77 | I6: 522.8 | J6: 661.62 | K6: =SUM(B6:J6)
A7: ISS retido de terceiros | B7: 0 | C7: 0 | D7: 0 | E7: 0 | F7: 38.92 | G7: 0 | H7: 0 | I7: 0 | J7: 0 | K7: =SUM(B7:J7)
